scanctl/__init__.py
scanctl/cli.py
scanctl/github.py
scanctl/shell.py
scanctl/whitesource.py
scanctl-0.5.0.dist-info/METADATA
scanctl-0.5.0.dist-info/RECORD
scanctl-0.5.0.dist-info/WHEEL
scanctl-0.5.0.dist-info/entry_points.txt
scanctl-0.5.0.dist-info/top_level.txt
