Metadata-Version: 2.1
Name: scanctl
Version: 0.5.0
Summary: A tool to facilitate managing whitesource data
Home-page: https://github.com/spotify/scanctl
Author: Spotify
Author-email: opensource@spotify.com
Maintainer: Spotify
Maintainer-email: opensource@spotify.com
License: Apache-2.0
Keywords: foss
Platform: UNKNOWN
Classifier: Development Status :: 3 - Alpha
Classifier: License :: OSI Approved :: Apache Software License
Classifier: Programming Language :: Python
Classifier: Programming Language :: Python :: 3
Classifier: Programming Language :: Python :: 3.6
Classifier: Programming Language :: Python :: Implementation :: CPython
Classifier: Programming Language :: Python :: Implementation :: PyPy
Classifier: Topic :: Software Development :: Libraries
Requires-Dist: attrs
Requires-Dist: click
Requires-Dist: PyGithub
Requires-Dist: PyJWT
Requires-Dist: pyyaml
Requires-Dist: requests
Requires-Dist: ulogger
